{
  "_fv": 13,
  "_type": "recipe",
  "definition": {
    "recipeType": "Crafting",
    "xpReward": 0.0,
    "cookingTime": 200,
    "recipeRetstackSize": 3,
    "group": "",
    "recipeShapeless": false,
    "recipeSlots": [
      {
        "value": "CUSTOM:DarkerLog"
      },
      {
        "value": "CUSTOM:DarkerLog"
      },
      {
        "value": ""
      },
      {
        "value": "CUSTOM:DarkerLog"
      },
      {
        "value": "CUSTOM:DarkerLog"
      },
      {
        "value": ""
      },
      {
        "value": ""
      },
      {
        "value": ""
      },
      {
        "value": ""
      }
    ],
    "recipeReturnStack": {
      "value": "CUSTOM:DarkerWood"
    },
    "name": "darker_wood_recipe",
    "namespace": "mod"
  }
}