{
  "_fv": 15,
  "_type": "tool",
  "definition": {
    "renderType": 0,
    "texture": "phantium_pickaxe",
    "customModelName": "Normal",
    "name": "Phantium Pickaxe",
    "specialInfo": [],
    "creativeTab": {
      "value": "TOOLS"
    },
    "toolType": "Pickaxe",
    "harvestLevel": 4,
    "efficiency": 9.0,
    "attackSpeed": 1.0,
    "enchantability": 27,
    "damageVsEntity": 4.0,
    "usageCount": 614,
    "blocksAffected": [],
    "hasGlow": false,
    "repairItems": [
      {
        "value": "CUSTOM:Phantium"
      }
    ],
    "immuneToFire": false,
    "stayInGridWhenCrafting": false,
    "damageOnCrafting": false
  }
}